echo_logger/__init__.py
echo_logger/echo_logger.py
echo_logger-0.1.6.dist-info/LICENSE
echo_logger-0.1.6.dist-info/METADATA
echo_logger-0.1.6.dist-info/WHEEL
echo_logger-0.1.6.dist-info/top_level.txt
echo_logger-0.1.6.dist-info/RECORD
