Metadata-Version: 2.1
Name: echo_logger
Version: 0.1.6
Summary: A simple logger for python, with color and time
Home-page: https://github.com/void-echo/echo_logger/
Author: Echo Void
Author-email: void-echo@outlook.com
Classifier: Programming Language :: Python :: 3
Classifier: License :: OSI Approved :: MIT License
Classifier: Operating System :: OS Independent
License-File: LICENSE
Requires-Dist: requests
Requires-Dist: loguru
